kssm-searcher/__init__.py
kssm-searcher/searcher.py
searcher/__init__.py
searcher/searcher.py
kssm_searcher-0.1.3.dist-info/LICENSE
kssm_searcher-0.1.3.dist-info/METADATA
kssm_searcher-0.1.3.dist-info/WHEEL
kssm_searcher-0.1.3.dist-info/entry_points.txt
kssm_searcher-0.1.3.dist-info/top_level.txt
kssm_searcher-0.1.3.dist-info/RECORD
