Metadata-Version: 2.1
Name: kssm-searcher
Version: 0.1.3
Summary: Herramienta para extraer informacion de documentos localizados en un directorio en base a keywords.
Home-page: https://gitlab.com/Karlossam/searcher
Author: Kssm
Author-email: your.email@example.com
Classifier: Programming Language :: Python :: 3
Classifier: License :: OSI Approved :: MIT License
Classifier: Operating System :: Unix
Requires-Python: >=3.6
License-File: LICENSE
Requires-Dist: PyPDF2
Requires-Dist: textract
